ygojson/__init__.py
ygojson/__main__.py
ygojson/database.py
ygojson/version.py
ygojson/importers/__init__.py
ygojson/importers/yamlyugi.py
ygojson/importers/ygoprodeck.py
ygojson/importers/yugipedia.py
ygojson-0.5.1.dist-info/LICENSE
ygojson-0.5.1.dist-info/METADATA
ygojson-0.5.1.dist-info/WHEEL
ygojson-0.5.1.dist-info/entry_points.txt
ygojson-0.5.1.dist-info/top_level.txt
ygojson-0.5.1.dist-info/RECORD
