Metadata-Version: 2.1
Name: ygojson
Version: 0.5.1
Summary: Generate and manipulate Yugioh card and set data.
Home-page: https://github.com/iconmaster5326/YGOJSON
Author: iconmaster5326
Keywords: yugioh,ygo,ygojson
Classifier: Development Status :: 3 - Alpha
Classifier: Intended Audience :: End Users/Desktop
Classifier: Topic :: Games/Entertainment
Classifier: License :: OSI Approved :: MIT License
Classifier: Programming Language :: Python :: 3
Requires-Python: >=3.8, <4
License-File: LICENSE
Requires-Dist: requests
Requires-Dist: wikitextparser
Requires-Dist: tqdm
Provides-Extra: dev
Requires-Dist: pre-commit ; extra == 'dev'
Provides-Extra: test
Requires-Dist: jsonschema ; extra == 'test'
